simditor/__init__.py
simditor/fields.py
simditor/image_processing.py
simditor/urls.py
simditor/utils.py
simditor/views.py
simditor/widgets.py
simditor/image/__init__.py
simditor/image/dummy_backend.py
simditor/image/pillow_backend.py
simditor/static/simditor/.DS_Store
simditor/static/simditor/simditor-init.js
simditor/static/simditor/fonts/icomoon.eot
simditor/static/simditor/fonts/icomoon.svg
simditor/static/simditor/fonts/icomoon.ttf
simditor/static/simditor/fonts/icomoon.woff
simditor/static/simditor/fonts/selection.json
simditor/static/simditor/images/.DS_Store
simditor/static/simditor/images/image.png
simditor/static/simditor/images/emoji/+1.png
simditor/static/simditor/images/emoji/-1.png
simditor/static/simditor/images/emoji/100.png
simditor/static/simditor/images/emoji/109.png
simditor/static/simditor/images/emoji/1234.png
simditor/static/simditor/images/emoji/a.png
simditor/static/simditor/images/emoji/ab.png
simditor/static/simditor/images/emoji/abc.png
simditor/static/simditor/images/emoji/abcd.png
simditor/static/simditor/images/emoji/accept.png
simditor/static/simditor/images/emoji/aerial_tramway.png
simditor/static/simditor/images/emoji/airplane.png
simditor/static/simditor/images/emoji/alarm_clock.png
simditor/static/simditor/images/emoji/alien.png
simditor/static/simditor/images/emoji/ambulance.png
simditor/static/simditor/images/emoji/anchor.png
simditor/static/simditor/images/emoji/angel.png
simditor/static/simditor/images/emoji/anger.png
simditor/static/simditor/images/emoji/angry.png
simditor/static/simditor/images/emoji/anguished.png
simditor/static/simditor/images/emoji/ant.png
simditor/static/simditor/images/emoji/apple.png
simditor/static/simditor/images/emoji/aquarius.png
simditor/static/simditor/images/emoji/aries.png
simditor/static/simditor/images/emoji/arrow_backward.png
simditor/static/simditor/images/emoji/arrow_double_down.png
simditor/static/simditor/images/emoji/arrow_double_up.png
django_simditor2-0.2.dist-info/LICENSE
django_simditor2-0.2.dist-info/METADATA
django_simditor2-0.2.dist-info/WHEEL
django_simditor2-0.2.dist-info/top_level.txt
django_simditor2-0.2.dist-info/RECORD
