Metadata-Version: 2.1
Name: django-simditor2
Version: 0.2
Summary: A Django admin Simditor integration.
Home-page: https://github.com/sai628/django-simditor2
Author: Sai628
Author-email: sai100628@gmail.com
License: MIT License
Keywords: Django admin Simditor integration
Classifier: Programming Language :: Python
Classifier: Programming Language :: Python :: 2.7
Classifier: Programming Language :: Python :: 3.3
Classifier: Programming Language :: Python :: 3.4
Classifier: Programming Language :: Python :: 3.5
Classifier: License :: OSI Approved :: MIT License
Classifier: Operating System :: OS Independent
Classifier: Framework :: Django
Classifier: Intended Audience :: Developers
Classifier: Topic :: Internet :: WWW/HTTP :: Dynamic Content
License-File: LICENSE
Requires-Dist: Django
Requires-Dist: pillow
